setup.py
rathilang/__init__.py
rathilang/__main__.py
rathilang/cli.py
rathilang/interpreter.py
rathilang/translator.py
rathilang-1.1.2.dist-info/LICENSE.txt
rathilang-1.1.2.dist-info/METADATA
rathilang-1.1.2.dist-info/WHEEL
rathilang-1.1.2.dist-info/entry_points.txt
rathilang-1.1.2.dist-info/top_level.txt
rathilang-1.1.2.dist-info/RECORD
