Metadata-Version: 2.1
Name: rathilang
Version: 1.1.2
Summary: A brainfuck derivative based on the the characteristics of Aashutosh Rathi
Home-page: https://github.com/thepushkarp/rathilang
Author: Pushkar Patel
Author-email: thepushkarp@gmail.com
License: MIT
Keywords: esoteric programming language brainfuck aashutoshrathi
Platform: UNKNOWN
Classifier: Development Status :: 4 - Beta
Classifier: Environment :: Console
Classifier: Intended Audience :: Developers
Classifier: Intended Audience :: Science/Research
Classifier: License :: OSI Approved :: MIT License
Classifier: Operating System :: OS Independent
Classifier: Programming Language :: Python
Classifier: Programming Language :: Python :: 3
Classifier: Programming Language :: Python :: 3.4
Classifier: Programming Language :: Python :: 3.5
Classifier: Programming Language :: Python :: 3.6
Classifier: Programming Language :: Python :: 3.7
Classifier: Programming Language :: Python :: Implementation :: PyPy
Requires-Dist: ply
